[
    {
        "outputFile": "D:\\Android Projects\\GetMyLatLongExample\\app\\build\\intermediates\\incremental\\mergeDebugResources\\merged.dir\\values-w480dp-v13\\values-w480dp-v13.xml",
        "map": [
            {
                "to": {
                    "startLine": 2,
                    "startColumn": 4,
                    "startOffset": 55,
                    "endColumn": 61,
                    "endOffset": 112
                },
                "from": {
                    "file": "D:\\Android Projects\\GetMyLatLongExample\\app\\build\\intermediates\\exploded-aar\\com.android.support\\appcompat-v7\\23.1.0\\res\\values-w480dp\\values-w480dp.xml",
                    "position": {
                        "startLine": 4,
                        "startColumn": 4,
                        "startOffset": 289,
                        "endColumn": 61,
                        "endOffset": 346
                    }
                }
            },
            {
                "to": {
                    "startLine": 3,
                    "startColumn": 4,
                    "startOffset": 117,
                    "endColumn": 71,
                    "endOffset": 184
                },
                "from": {
                    "file": "D:\\Android Projects\\GetMyLatLongExample\\app\\build\\intermediates\\exploded-aar\\com.android.support\\appcompat-v7\\23.1.0\\res\\values-w480dp\\values-w480dp.xml",
                    "position": {
                        "startLine": 7,
                        "startColumn": 4,
                        "startOffset": 586,
                        "endColumn": 71,
                        "endOffset": 653
                    }
                }
            }
        ]
    },
    {
        "outputFile": "F:\\GetMyLatLongExample\\app\\build\\intermediates\\incremental\\mergeDebugResources\\merged.dir\\values-w480dp-v13\\values-w480dp-v13.xml",
        "map": [
            {
                "to": {
                    "startLine": 2,
                    "startColumn": 4,
                    "startOffset": 55,
                    "endColumn": 61,
                    "endOffset": 112
                },
                "from": {
                    "file": "F:\\GetMyLatLongExample\\app\\build\\intermediates\\exploded-aar\\com.android.support\\appcompat-v7\\23.1.0\\res\\values-w480dp\\values-w480dp.xml",
                    "position": {
                        "startLine": 4,
                        "startColumn": 4,
                        "startOffset": 289,
                        "endColumn": 61,
                        "endOffset": 346
                    }
                }
            },
            {
                "to": {
                    "startLine": 3,
                    "startColumn": 4,
                    "startOffset": 117,
                    "endColumn": 71,
                    "endOffset": 184
                },
                "from": {
                    "file": "F:\\GetMyLatLongExample\\app\\build\\intermediates\\exploded-aar\\com.android.support\\appcompat-v7\\23.1.0\\res\\values-w480dp\\values-w480dp.xml",
                    "position": {
                        "startLine": 7,
                        "startColumn": 4,
                        "startOffset": 586,
                        "endColumn": 71,
                        "endOffset": 653
                    }
                }
            }
        ]
    },
    {
        "outputFile": "D:\\akku\\getmylatlong1.2\\GetMyLatLongExample1\\app\\build\\intermediates\\incremental\\mergeDebugResources\\merged.dir\\values-w480dp-v13\\values-w480dp-v13.xml",
        "map": [
            {
                "to": {
                    "startLine": 2,
                    "startColumn": 4,
                    "startOffset": 55,
                    "endColumn": 61,
                    "endOffset": 112
                },
                "from": {
                    "file": "D:\\akku\\getmylatlong1.2\\GetMyLatLongExample1\\app\\build\\intermediates\\exploded-aar\\com.android.support\\appcompat-v7\\23.1.0\\res\\values-w480dp\\values-w480dp.xml",
                    "position": {
                        "startLine": 4,
                        "startColumn": 4,
                        "startOffset": 289,
                        "endColumn": 61,
                        "endOffset": 346
                    }
                }
            },
            {
                "to": {
                    "startLine": 3,
                    "startColumn": 4,
                    "startOffset": 117,
                    "endColumn": 71,
                    "endOffset": 184
                },
                "from": {
                    "file": "D:\\akku\\getmylatlong1.2\\GetMyLatLongExample1\\app\\build\\intermediates\\exploded-aar\\com.android.support\\appcompat-v7\\23.1.0\\res\\values-w480dp\\values-w480dp.xml",
                    "position": {
                        "startLine": 7,
                        "startColumn": 4,
                        "startOffset": 586,
                        "endColumn": 71,
                        "endOffset": 653
                    }
                }
            }
        ]
    },
    {
        "outputFile": "D:\\akku\\1.7\\GetMyLatLongExample1\\app\\build\\intermediates\\incremental\\mergeDebugResources\\merged.dir\\values-w480dp-v13\\values-w480dp-v13.xml",
        "map": [
            {
                "to": {
                    "startLine": 2,
                    "startColumn": 4,
                    "startOffset": 55,
                    "endColumn": 61,
                    "endOffset": 112
                },
                "from": {
                    "file": "D:\\akku\\1.7\\GetMyLatLongExample1\\app\\build\\intermediates\\exploded-aar\\com.android.support\\appcompat-v7\\23.1.0\\res\\values-w480dp\\values-w480dp.xml",
                    "position": {
                        "startLine": 4,
                        "startColumn": 4,
                        "startOffset": 289,
                        "endColumn": 61,
                        "endOffset": 346
                    }
                }
            },
            {
                "to": {
                    "startLine": 3,
                    "startColumn": 4,
                    "startOffset": 117,
                    "endColumn": 71,
                    "endOffset": 184
                },
                "from": {
                    "file": "D:\\akku\\1.7\\GetMyLatLongExample1\\app\\build\\intermediates\\exploded-aar\\com.android.support\\appcompat-v7\\23.1.0\\res\\values-w480dp\\values-w480dp.xml",
                    "position": {
                        "startLine": 7,
                        "startColumn": 4,
                        "startOffset": 586,
                        "endColumn": 71,
                        "endOffset": 653
                    }
                }
            }
        ]
    },
    {
        "outputFile": "D:\\akku\\GetMyLatLongExample1\\app\\build\\intermediates\\incremental\\mergeDebugResources\\merged.dir\\values-w480dp-v13\\values-w480dp-v13.xml",
        "map": [
            {
                "to": {
                    "startLine": 2,
                    "startColumn": 4,
                    "startOffset": 55,
                    "endColumn": 61,
                    "endOffset": 112
                },
                "from": {
                    "file": "D:\\akku\\GetMyLatLongExample1\\app\\build\\intermediates\\exploded-aar\\com.android.support\\appcompat-v7\\23.1.0\\res\\values-w480dp\\values-w480dp.xml",
                    "position": {
                        "startLine": 4,
                        "startColumn": 4,
                        "startOffset": 289,
                        "endColumn": 61,
                        "endOffset": 346
                    }
                }
            },
            {
                "to": {
                    "startLine": 3,
                    "startColumn": 4,
                    "startOffset": 117,
                    "endColumn": 71,
                    "endOffset": 184
                },
                "from": {
                    "file": "D:\\akku\\GetMyLatLongExample1\\app\\build\\intermediates\\exploded-aar\\com.android.support\\appcompat-v7\\23.1.0\\res\\values-w480dp\\values-w480dp.xml",
                    "position": {
                        "startLine": 7,
                        "startColumn": 4,
                        "startOffset": 586,
                        "endColumn": 71,
                        "endOffset": 653
                    }
                }
            }
        ]
    },
    {
        "outputFile": "C:\\Users\\admin\\AndroidStudioProjects\\GetMyLatLongExample\\app\\build\\intermediates\\incremental\\mergeDebugResources\\merged.dir\\values-w480dp-v13\\values-w480dp-v13.xml",
        "map": [
            {
                "to": {
                    "startLine": 2,
                    "startColumn": 4,
                    "startOffset": 55,
                    "endColumn": 61,
                    "endOffset": 112
                },
                "from": {
                    "file": "C:\\Users\\admin\\AndroidStudioProjects\\GetMyLatLongExample\\app\\build\\intermediates\\exploded-aar\\com.android.support\\appcompat-v7\\23.1.0\\res\\values-w480dp\\values-w480dp.xml",
                    "position": {
                        "startLine": 4,
                        "startColumn": 4,
                        "startOffset": 289,
                        "endColumn": 61,
                        "endOffset": 346
                    }
                }
            },
            {
                "to": {
                    "startLine": 3,
                    "startColumn": 4,
                    "startOffset": 117,
                    "endColumn": 71,
                    "endOffset": 184
                },
                "from": {
                    "file": "C:\\Users\\admin\\AndroidStudioProjects\\GetMyLatLongExample\\app\\build\\intermediates\\exploded-aar\\com.android.support\\appcompat-v7\\23.1.0\\res\\values-w480dp\\values-w480dp.xml",
                    "position": {
                        "startLine": 7,
                        "startColumn": 4,
                        "startOffset": 586,
                        "endColumn": 71,
                        "endOffset": 653
                    }
                }
            }
        ]
    },
    {
        "outputFile": "D:\\IT welcome juniors\\GetMyLatLongExample\\app\\build\\intermediates\\incremental\\mergeDebugResources\\merged.dir\\values-w480dp-v13\\values-w480dp-v13.xml",
        "map": [
            {
                "to": {
                    "startLine": 2,
                    "startColumn": 4,
                    "startOffset": 55,
                    "endColumn": 61,
                    "endOffset": 112
                },
                "from": {
                    "file": "D:\\IT welcome juniors\\GetMyLatLongExample\\app\\build\\intermediates\\exploded-aar\\com.android.support\\appcompat-v7\\23.1.0\\res\\values-w480dp\\values-w480dp.xml",
                    "position": {
                        "startLine": 4,
                        "startColumn": 4,
                        "startOffset": 289,
                        "endColumn": 61,
                        "endOffset": 346
                    }
                }
            },
            {
                "to": {
                    "startLine": 3,
                    "startColumn": 4,
                    "startOffset": 117,
                    "endColumn": 71,
                    "endOffset": 184
                },
                "from": {
                    "file": "D:\\IT welcome juniors\\GetMyLatLongExample\\app\\build\\intermediates\\exploded-aar\\com.android.support\\appcompat-v7\\23.1.0\\res\\values-w480dp\\values-w480dp.xml",
                    "position": {
                        "startLine": 7,
                        "startColumn": 4,
                        "startOffset": 586,
                        "endColumn": 71,
                        "endOffset": 653
                    }
                }
            }
        ]
    },
    {
        "outputFile": "D:\\adi niu\\GetMyLatLongExample1\\app\\build\\intermediates\\incremental\\mergeDebugResources\\merged.dir\\values-w480dp-v13\\values-w480dp-v13.xml",
        "map": [
            {
                "to": {
                    "startLine": 2,
                    "startColumn": 4,
                    "startOffset": 55,
                    "endColumn": 61,
                    "endOffset": 112
                },
                "from": {
                    "file": "D:\\adi niu\\GetMyLatLongExample1\\app\\build\\intermediates\\exploded-aar\\com.android.support\\appcompat-v7\\23.1.0\\res\\values-w480dp\\values-w480dp.xml",
                    "position": {
                        "startLine": 4,
                        "startColumn": 4,
                        "startOffset": 289,
                        "endColumn": 61,
                        "endOffset": 346
                    }
                }
            },
            {
                "to": {
                    "startLine": 3,
                    "startColumn": 4,
                    "startOffset": 117,
                    "endColumn": 71,
                    "endOffset": 184
                },
                "from": {
                    "file": "D:\\adi niu\\GetMyLatLongExample1\\app\\build\\intermediates\\exploded-aar\\com.android.support\\appcompat-v7\\23.1.0\\res\\values-w480dp\\values-w480dp.xml",
                    "position": {
                        "startLine": 7,
                        "startColumn": 4,
                        "startOffset": 586,
                        "endColumn": 71,
                        "endOffset": 653
                    }
                }
            }
        ]
    },
    {
        "outputFile": "D:\\Android Projects\\GetMyLatLongExample1\\app\\build\\intermediates\\incremental\\mergeDebugResources\\merged.dir\\values-w480dp-v13\\values-w480dp-v13.xml",
        "map": [
            {
                "to": {
                    "startLine": 2,
                    "startColumn": 4,
                    "startOffset": 55,
                    "endColumn": 61,
                    "endOffset": 112
                },
                "from": {
                    "file": "D:\\Android Projects\\GetMyLatLongExample1\\app\\build\\intermediates\\exploded-aar\\com.android.support\\appcompat-v7\\23.1.0\\res\\values-w480dp\\values-w480dp.xml",
                    "position": {
                        "startLine": 4,
                        "startColumn": 4,
                        "startOffset": 289,
                        "endColumn": 61,
                        "endOffset": 346
                    }
                }
            },
            {
                "to": {
                    "startLine": 3,
                    "startColumn": 4,
                    "startOffset": 117,
                    "endColumn": 71,
                    "endOffset": 184
                },
                "from": {
                    "file": "D:\\Android Projects\\GetMyLatLongExample1\\app\\build\\intermediates\\exploded-aar\\com.android.support\\appcompat-v7\\23.1.0\\res\\values-w480dp\\values-w480dp.xml",
                    "position": {
                        "startLine": 7,
                        "startColumn": 4,
                        "startOffset": 586,
                        "endColumn": 71,
                        "endOffset": 653
                    }
                }
            }
        ]
    },
    {
        "outputFile": "D:\\akku\\1.10\\GetMyLatLongExample1\\app\\build\\intermediates\\incremental\\mergeDebugResources\\merged.dir\\values-w480dp-v13\\values-w480dp-v13.xml",
        "map": [
            {
                "to": {
                    "startLine": 2,
                    "startColumn": 4,
                    "startOffset": 55,
                    "endColumn": 61,
                    "endOffset": 112
                },
                "from": {
                    "file": "D:\\akku\\1.10\\GetMyLatLongExample1\\app\\build\\intermediates\\exploded-aar\\com.android.support\\appcompat-v7\\23.1.0\\res\\values-w480dp\\values-w480dp.xml",
                    "position": {
                        "startLine": 4,
                        "startColumn": 4,
                        "startOffset": 289,
                        "endColumn": 61,
                        "endOffset": 346
                    }
                }
            },
            {
                "to": {
                    "startLine": 3,
                    "startColumn": 4,
                    "startOffset": 117,
                    "endColumn": 71,
                    "endOffset": 184
                },
                "from": {
                    "file": "D:\\akku\\1.10\\GetMyLatLongExample1\\app\\build\\intermediates\\exploded-aar\\com.android.support\\appcompat-v7\\23.1.0\\res\\values-w480dp\\values-w480dp.xml",
                    "position": {
                        "startLine": 7,
                        "startColumn": 4,
                        "startOffset": 586,
                        "endColumn": 71,
                        "endOffset": 653
                    }
                }
            }
        ]
    },
    {
        "outputFile": "D:\\akku\\1.9\\GetMyLatLongExample1\\app\\build\\intermediates\\incremental\\mergeDebugResources\\merged.dir\\values-w480dp-v13\\values-w480dp-v13.xml",
        "map": [
            {
                "to": {
                    "startLine": 2,
                    "startColumn": 4,
                    "startOffset": 55,
                    "endColumn": 61,
                    "endOffset": 112
                },
                "from": {
                    "file": "D:\\akku\\1.9\\GetMyLatLongExample1\\app\\build\\intermediates\\exploded-aar\\com.android.support\\appcompat-v7\\23.1.0\\res\\values-w480dp\\values-w480dp.xml",
                    "position": {
                        "startLine": 4,
                        "startColumn": 4,
                        "startOffset": 289,
                        "endColumn": 61,
                        "endOffset": 346
                    }
                }
            },
            {
                "to": {
                    "startLine": 3,
                    "startColumn": 4,
                    "startOffset": 117,
                    "endColumn": 71,
                    "endOffset": 184
                },
                "from": {
                    "file": "D:\\akku\\1.9\\GetMyLatLongExample1\\app\\build\\intermediates\\exploded-aar\\com.android.support\\appcompat-v7\\23.1.0\\res\\values-w480dp\\values-w480dp.xml",
                    "position": {
                        "startLine": 7,
                        "startColumn": 4,
                        "startOffset": 586,
                        "endColumn": 71,
                        "endOffset": 653
                    }
                }
            }
        ]
    }
]